{
  "data": {
    "type": "fixture-statistics",
    "id": "EN2pgbwwEd",
    "attributes": {
      "matchsheet_status": "completed",
      "score": {
        "home": {
          "half_time": null,
          "full_time": "0",
          "extra_half_time": null,
          "extra_full_time": null,
          "penalties": null
        },
        "away": {
          "half_time": null,
          "full_time": "1",
          "extra_half_time": null,
          "extra_full_time": null,
          "penalties": null
        },
        "forfeit_team_id": null
      },
      "referees": [
        {
          "id": "vdWoVnwvdO",
          "referee_role": "cr",
          "status": "accepted",
          "presence": "present",
          "first_name": "Bernadette",
          "last_name": "Blake"
        },
        {
          "id": "wNlGpy0Dmj",
          "referee_role": "ar1",
          "status": "accepted",
          "presence": "present",
          "first_name": "Timothy",
          "last_name": "Cooper"
        },
        {
          "id": "ydoJ8WBDKD",
          "referee_role": "ar2",
          "status": "accepted",
          "presence": "present",
          "first_name": "Charlie",
          "last_name": "Rodney"
        }
      ],
      "members": [
        {
          "id": "nmYnXAkBpN",
          "matchsheet_member_id": "K3rl8qy03N",
          "team_id": "xNx98V9yKk",
          "first_name": "Craig",
          "last_name": "Slater",
          "federation_number": "90702070",
          "shirt_number": null,
          "role_name": "Coach",
          "role_slug": "coach",
          "is_guest": false
        },
        {
          "id": "RNEp4REamv",
          "matchsheet_member_id": "do753Pb27d",
          "team_id": "BdVn5rGPdE",
          "first_name": "Joel",
          "last_name": "Everingham",
          "federation_number": "83619809",
          "shirt_number": "52",
          "role_name": "Player",
          "role_slug": "player",
          "is_guest": false
        },
        {
          "id": "8NODV3r2KZ",
          "matchsheet_member_id": "KRDYLlMB7m",
          "team_id": "BdVn5rGPdE",
          "first_name": "Basl",
          "last_name": "Hasan",
          "federation_number": "10965490",
          "shirt_number": "",
          "role_name": "Player",
          "role_slug": "player",
          "is_guest": false
        },
        {
          "id": "ydoJq4PRKD",
          "matchsheet_member_id": "dkzXePjZ4K",
          "team_id": "BdVn5rGPdE",
          "first_name": "Dion",
          "last_name": "Bonetti",
          "federation_number": "79616744",
          "shirt_number": "",
          "role_name": "Player",
          "role_slug": "player",
          "is_guest": false
        },
        {
          "id": "Wdg457zqmR",
          "matchsheet_member_id": "meL5lqRw1d",
          "team_id": "BdVn5rGPdE",
          "first_name": "Mojtaba",
          "last_name": "Rahimi",
          "federation_number": "11613759",
          "shirt_number": "42-1",
          "role_name": "Player",
          "role_slug": "player",
          "is_guest": false
        },
        {
          "id": "8NO51Pj52d",
          "matchsheet_member_id": "NQGzBk1nrd",
          "team_id": "BdVn5rGPdE",
          "first_name": "Anderon",
          "last_name": "Babic",
          "federation_number": "90095839",
          "shirt_number": "44",
          "role_name": "Player",
          "role_slug": "player",
          "is_guest": false
        },
        {
          "id": "1K3p5l1n7d",
          "matchsheet_member_id": "d46XE2pX0N",
          "team_id": "BdVn5rGPdE",
          "first_name": "Daryan",
          "last_name": "Khalaf",
          "federation_number": "90488929",
          "shirt_number": "53",
          "role_name": "Player",
          "role_slug": "player",
          "is_guest": false
        },
        {
          "id": "bd9pOEpvwK",
          "matchsheet_member_id": "Nq8Xx948ym",
          "team_id": "BdVn5rGPdE",
          "first_name": "Mitchell",
          "last_name": "Gayler",
          "federation_number": "90830808",
          "shirt_number": "51",
          "role_name": "Player",
          "role_slug": "player",
          "is_guest": false
        },
        {
          "id": "xNx5yV5QAK",
          "matchsheet_member_id": "N6EXMARxpm",
          "team_id": "BdVn5rGPdE",
          "first_name": "Jasper",
          "last_name": "Babic",
          "federation_number": "90820441",
          "shirt_number": "49-1",
          "role_name": "Player",
          "role_slug": "player",
          "is_guest": false
        },
        {
          "id": "gdM6PY6JZm",
          "matchsheet_member_id": "dDZDX8bEJN",
          "team_id": "BdVn5rGPdE",
          "first_name": "Logan",
          "last_name": "McCann-Dillon",
          "federation_number": "90812341",
          "shirt_number": "68",
          "role_name": "Player",
          "role_slug": "player",
          "is_guest": false
        },
        {
          "id": "gdM6PYBl7m",
          "matchsheet_member_id": "dWkJ6rDlGd",
          "team_id": "BdVn5rGPdE",
          "first_name": "Ali",
          "last_name": "Zahidi",
          "federation_number": "90346491",
          "shirt_number": "46",
          "role_name": "Player",
          "role_slug": "player",
          "is_guest": false
        },
        {
          "id": "nm79ejZVKO",
          "matchsheet_member_id": "m1gx9g1JnK",
          "team_id": "BdVn5rGPdE",
          "first_name": "Natheer",
          "last_name": "Al Hasan",
          "federation_number": "11017279",
          "shirt_number": null,
          "role_name": "Coach",
          "role_slug": "coach",
          "is_guest": false
        },
        {
          "id": "wNl4VxaGAN",
          "matchsheet_member_id": "dWkJQRbgjd",
          "team_id": "BdVn5rGPdE",
          "first_name": "Sibhan",
          "last_name": "Khalaf",
          "federation_number": "90288098",
          "shirt_number": "48",
          "role_name": "Player",
          "role_slug": "player",
          "is_guest": false
        },
        {
          "id": "nm7PkyP7DN",
          "matchsheet_member_id": "m1gx90pbrK",
          "team_id": "BdVn5rGPdE",
          "first_name": "Malik",
          "last_name": "Murad",
          "federation_number": "90707214",
          "shirt_number": "56",
          "role_name": "Player",
          "role_slug": "player",
          "is_guest": false
        },
        {
          "id": "BdDbPGzvgN",
          "matchsheet_member_id": "Nq8XVErpjm",
          "team_id": "BdVn5rGPdE",
          "first_name": "Thomas",
          "last_name": "Hasler",
          "federation_number": "90839032",
          "shirt_number": "",
          "role_name": "Player",
          "role_slug": "player",
          "is_guest": false
        },
        {
          "id": "vdWDOxPBGm",
          "matchsheet_member_id": "d46XoqyypN",
          "team_id": "BdVn5rGPdE",
          "first_name": "Nawzad",
          "last_name": "Ato",
          "federation_number": "90836581",
          "shirt_number": "59",
          "role_name": "Player",
          "role_slug": "player",
          "is_guest": false
        },
        {
          "id": "yKJJPkeR3K",
          "matchsheet_member_id": "mXlJvxaa4m",
          "team_id": "BdVn5rGPdE",
          "first_name": "Rayan",
          "last_name": "sharkani",
          "federation_number": "90165435",
          "shirt_number": "43",
          "role_name": "Player",
          "role_slug": "player",
          "is_guest": false
        },
        {
          "id": "1K3vy1p9NQ",
          "matchsheet_member_id": "m82pXOXqzK",
          "team_id": "BdVn5rGPdE",
          "first_name": "Ahmad",
          "last_name": "Rahman",
          "federation_number": "11407520",
          "shirt_number": "58",
          "role_name": "Player",
          "role_slug": "player",
          "is_guest": false
        },
        {
          "id": "am14p00Lnd",
          "matchsheet_member_id": "m82pXDgbbK",
          "team_id": "BdVn5rGPdE",
          "first_name": "Chris",
          "last_name": "Ayton",
          "federation_number": "90182980",
          "shirt_number": null,
          "role_name": "Coach",
          "role_slug": "coach",
          "is_guest": false
        },
        {
          "id": "Ome0Byk0d0",
          "matchsheet_member_id": "K3rYBYz4BN",
          "team_id": "xNx98V9yKk",
          "first_name": "Alexander",
          "last_name": "English",
          "federation_number": "77054237",
          "shirt_number": "58",
          "role_name": "Player",
          "role_slug": "player",
          "is_guest": false
        },
        {
          "id": "MNGoZbL2NA",
          "matchsheet_member_id": "Nq8W4W9zJm",
          "team_id": "xNx98V9yKk",
          "first_name": "Arnold",
          "last_name": "Freeman",
          "federation_number": "10449540",
          "shirt_number": null,
          "role_name": "Manager",
          "role_slug": "manager",
          "is_guest": false
        },
        {
          "id": "ZKR52ln47N",
          "matchsheet_member_id": "KRDv5vEOjm",
          "team_id": "xNx98V9yKk",
          "first_name": "Cameron",
          "last_name": "Heidtmann",
          "federation_number": "81957599",
          "shirt_number": "53",
          "role_name": "Player",
          "role_slug": "player",
          "is_guest": false
        },
        {
          "id": "BdDx6pRaxd",
          "matchsheet_member_id": "dkzvqvoMRK",
          "team_id": "xNx98V9yKk",
          "first_name": "Henry",
          "last_name": "MacIver",
          "federation_number": "80459514",
          "shirt_number": "46",
          "role_name": "Player",
          "role_slug": "player",
          "is_guest": false
        },
        {
          "id": "pN6pMazVpd",
          "matchsheet_member_id": "NQGnan7eJd",
          "team_id": "xNx98V9yKk",
          "first_name": "Harrison",
          "last_name": "Shorrock",
          "federation_number": "11761235",
          "shirt_number": "55",
          "role_name": "Player",
          "role_slug": "player",
          "is_guest": false
        },
        {
          "id": "BdDxXlqvgd",
          "matchsheet_member_id": "K3rYBYXkON",
          "team_id": "xNx98V9yKk",
          "first_name": "Max",
          "last_name": "Murray",
          "federation_number": "80522824",
          "shirt_number": "57",
          "role_name": "Player",
          "role_slug": "player",
          "is_guest": false
        },
        {
          "id": "2KpR4Gxjzm",
          "matchsheet_member_id": "mXlbQbGLnm",
          "team_id": "xNx98V9yKk",
          "first_name": "Noah",
          "last_name": "Block",
          "federation_number": "76910223",
          "shirt_number": "22",
          "role_name": "Player",
          "role_slug": "player",
          "is_guest": false
        },
        {
          "id": "emAnp5vLQN",
          "matchsheet_member_id": "mXlbQbzB6m",
          "team_id": "xNx98V9yKk",
          "first_name": "Isaac",
          "last_name": "Brown",
          "federation_number": "90179113",
          "shirt_number": "2",
          "role_name": "Player",
          "role_slug": "player",
          "is_guest": false
        },
        {
          "id": "pN6RqZZQAN",
          "matchsheet_member_id": "do7nOnD27d",
          "team_id": "xNx98V9yKk",
          "first_name": "Riley",
          "last_name": "Wilder",
          "federation_number": "90221336",
          "shirt_number": "47",
          "role_name": "Player",
          "role_slug": "player",
          "is_guest": false
        },
        {
          "id": "4KLl1VV5GK",
          "matchsheet_member_id": "m1gqnqDQkK",
          "team_id": "xNx98V9yKk",
          "first_name": "Zabir",
          "last_name": "Alam",
          "federation_number": "90131699",
          "shirt_number": "51",
          "role_name": "Player",
          "role_slug": "player",
          "is_guest": false
        },
        {
          "id": "MNGJ0j2AXm",
          "matchsheet_member_id": "dg9G6G7VXN",
          "team_id": "xNx98V9yKk",
          "first_name": "Liam",
          "last_name": "Payne",
          "federation_number": "90366864",
          "shirt_number": "59",
          "role_name": "Player",
          "role_slug": "player",
          "is_guest": false
        },
        {
          "id": "wNl4rkDr8N",
          "matchsheet_member_id": "mYOyzyvxyK",
          "team_id": "xNx98V9yKk",
          "first_name": "Geoffrey",
          "last_name": "Shaw",
          "federation_number": "11536420",
          "shirt_number": "48",
          "role_name": "Player",
          "role_slug": "player",
          "is_guest": false
        },
        {
          "id": "Pmj2avpakm",
          "matchsheet_member_id": "NEZpGpRraK",
          "team_id": "xNx98V9yKk",
          "first_name": "Lachlan",
          "last_name": "Li",
          "federation_number": "77664191",
          "shirt_number": "50",
          "role_name": "Player",
          "role_slug": "player",
          "is_guest": false
        },
        {
          "id": "am14GB9Jnd",
          "matchsheet_member_id": "KRDv5v7MAm",
          "team_id": "xNx98V9yKk",
          "first_name": "Harry",
          "last_name": "Robinson",
          "federation_number": "90342101",
          "shirt_number": "45",
          "role_name": "Player",
          "role_slug": "player",
          "is_guest": false
        },
        {
          "id": "bd9pOrYbRK",
          "matchsheet_member_id": "mXlbQbpQDm",
          "team_id": "xNx98V9yKk",
          "first_name": "Logan",
          "last_name": "Lovasz",
          "federation_number": "79354023",
          "shirt_number": "44",
          "role_name": "Player",
          "role_slug": "player",
          "is_guest": false
        },
        {
          "id": "MNGJXPM4bm",
          "matchsheet_member_id": "meL0j0D7Pd",
          "team_id": "xNx98V9yKk",
          "first_name": "Willem",
          "last_name": "Corkery",
          "federation_number": "90257718",
          "shirt_number": "56",
          "role_name": "Player",
          "role_slug": "player",
          "is_guest": false
        },
        {
          "id": "ld45MxkgAm",
          "matchsheet_member_id": "NEZpGp2YXK",
          "team_id": "xNx98V9yKk",
          "first_name": "sidney",
          "last_name": "vanleeuwen",
          "federation_number": "90977438",
          "shirt_number": "54",
          "role_name": "Player",
          "role_slug": "player",
          "is_guest": false
        },
        {
          "id": "lNbG9WPDKx",
          "matchsheet_member_id": "NQGnaLE2Ad",
          "team_id": "BdVn5rGPdE",
          "first_name": "Jovan Kheiri",
          "last_name": "ILYAS",
          "federation_number": "11618949",
          "shirt_number": "47",
          "role_name": "Player",
          "role_slug": "player",
          "is_guest": false
        },
        {
          "id": "pN6R47J1ON",
          "matchsheet_member_id": "mYOyz7BEbK",
          "team_id": "BdVn5rGPdE",
          "first_name": "Diyar",
          "last_name": "Aliko",
          "federation_number": "90835456",
          "shirt_number": "54",
          "role_name": "Player",
          "role_slug": "player",
          "is_guest": false
        },
        {
          "id": "nm7P233qaN",
          "matchsheet_member_id": "meL0vYZjGd",
          "team_id": "xNx98V9yKk",
          "first_name": "Jaxon",
          "last_name": "Apps",
          "federation_number": "76873595",
          "shirt_number": "52",
          "role_name": "Player",
          "role_slug": "player",
          "is_guest": false
        },
        {
          "id": "1K3pJYpPOd",
          "matchsheet_member_id": "N6EOQZ8pbm",
          "team_id": "xNx98V9yKk",
          "first_name": "Cayless",
          "last_name": "Richens",
          "federation_number": "90706112",
          "shirt_number": "49",
          "role_name": "Player",
          "role_slug": "player",
          "is_guest": false
        },
        {
          "id": "vmZpVWpkLK",
          "matchsheet_member_id": "Nq8WwYgW8m",
          "team_id": "BdVn5rGPdE",
          "first_name": "Malek",
          "last_name": "Khalaf",
          "federation_number": "90686196",
          "shirt_number": "57",
          "role_name": "Player",
          "role_slug": "player",
          "is_guest": false
        }
      ],
      "goals": [
        {
          "matchsheet_member_id": "meL0j0D7Pd",
          "team_id": "xNx98V9yKk",
          "minute": "77",
          "note": null,
          "own_goal": false,
          "penalty_kick": false,
          "game_section": "ft-second-half",
          "member": {
            "id": "MNGJXPM4bm",
            "matchsheet_member_id": "meL0j0D7Pd",
            "first_name": "Willem",
            "last_name": "Corkery",
            "federation_number": "90257718"
          }
        }
      ],
      "substitutions": [],
      "cards": [
        {
          "matchsheet_member_id": "meL5lqRw1d",
          "team_id": "BdVn5rGPdE",
          "minute": "40",
          "note": null,
          "game_section": "ft-first-half",
          "offence_code": {
            "name": "Y1 - Unsporting behaviour",
            "code": "Y1",
            "type": "Yellow Card",
            "override_color": null
          },
          "final_card": {
            "name": "Y1 - Unsporting behaviour",
            "code": "Y1",
            "type": "Yellow Card",
            "override_color": null
          },
          "member": {
            "id": "Wdg457zqmR",
            "matchsheet_member_id": "meL5lqRw1d",
            "first_name": "Mojtaba",
            "last_name": "Rahimi",
            "federation_number": "11613759"
          }
        },
        {
          "matchsheet_member_id": "N6EXMARxpm",
          "team_id": "BdVn5rGPdE",
          "minute": "42",
          "note": null,
          "game_section": "ft-first-half",
          "offence_code": {
            "name": "Y4 - Delaying the restart of play",
            "code": "Y4",
            "type": "Yellow Card",
            "override_color": null
          },
          "final_card": {
            "name": "Y4 - Delaying the restart of play",
            "code": "Y4",
            "type": "Yellow Card",
            "override_color": null
          },
          "member": {
            "id": "xNx5yV5QAK",
            "matchsheet_member_id": "N6EXMARxpm",
            "first_name": "Jasper",
            "last_name": "Babic",
            "federation_number": "90820441"
          }
        }
      ],
      "penalties": []
    }
  }
}